__init__.py
circular_queue.py
circular_queue-0.0.3.dist-info/LICENSE.md
circular_queue-0.0.3.dist-info/METADATA
circular_queue-0.0.3.dist-info/WHEEL
circular_queue-0.0.3.dist-info/top_level.txt
circular_queue-0.0.3.dist-info/RECORD
