Metadata-Version: 2.1
Name: circular-queue
Version: 0.0.3
Summary: A pythonic implementation of a circular queue
Author-email: Gui Luz <salgl@yahoo.com.br>
Project-URL: Homepage, https://github.com/Gui-Luz/circular-queue
Project-URL: Bug Tracker, https://github.com/Gui-Luz/circular-queue/issues
Classifier: Programming Language :: Python :: 3
Classifier: License :: OSI Approved :: MIT License
Classifier: Operating System :: OS Independent
Requires-Python: >=3.0
License-File: LICENSE.md
